{
	"configurations": [
		{
			"name": "Linux",
			"includePath": [
				"${workspaceFolder}/**",
				"/usr/local/include/**",
				"/usr/include/**",
				"/usr/local/include",
				"/usr/include/x86_64-linux-gnu",
				"/usr/include",
				"/usr/src/**",
				"/usr/local/include"
			],
			"compilerPath": "/usr/bin/gcc",
			"cStandard": "c11",
			"cppStandard": "c++11",
			"intelliSenseMode": "linux-gcc-x86",
			"compilerArgs": [
				""
			],
			"browse": {
				"path": [
					"${workspaceFolder}/**",
					"/usr/local/include",
					"/usr/include/x86_64-linux-gnu",
					"/usr/include",
					"/usr/include/**",
					"/usr/src/**",
					"/usr/local/include/**"
				],
				"limitSymbolsToIncludedHeaders": true,
				"databaseFilename": "${workspaceFolder}/.vscode/browse.vc.db"
			},
			"configurationProvider": "ms-vscode.cmake-tools"
		}
	],
	"version": 4
}